cherry_indexer/__init__.py
cherry_indexer/config/__init__.py
cherry_indexer/config/parser.py
cherry_indexer/utils/__init__.py
cherry_indexer/utils/logging_setup.py
cherry_indexer/utils/pipeline.py
cherry_indexer/writers/__init__.py
cherry_indexer/writers/aws_wrangler_s3.py
cherry_indexer/writers/base.py
cherry_indexer/writers/clickhouse.py
cherry_indexer/writers/local_parquet.py
cherry_indexer/writers/postgres.py
cherry_indexer/writers/s3.py
cherry_indexer/writers/writer.py
cherry_indexer-0.1.7.dist-info/LICENSE-APACHE
cherry_indexer-0.1.7.dist-info/LICENSE-MIT
cherry_indexer-0.1.7.dist-info/METADATA
cherry_indexer-0.1.7.dist-info/WHEEL
cherry_indexer-0.1.7.dist-info/top_level.txt
cherry_indexer-0.1.7.dist-info/RECORD
